{"/":{"style.a89de.css":{"type":"style","weight":1},"bundle.38f5b.js":{"type":"script","weight":1},"route-home.chunk.64aca.js":{"type":"script","weight":0.9}},"/signup":{"style.a89de.css":{"type":"style","weight":1},"bundle.38f5b.js":{"type":"script","weight":1},"route-signup.chunk.3b6c7.js":{"type":"script","weight":0.9}},"/reset-password":{"style.a89de.css":{"type":"style","weight":1},"bundle.38f5b.js":{"type":"script","weight":1},"route-reset-password.chunk.b98af.js":{"type":"script","weight":0.9}},"/recover-account":{"style.a89de.css":{"type":"style","weight":1},"bundle.38f5b.js":{"type":"script","weight":1},"route-recover-account.chunk.75f12.js":{"type":"script","weight":0.9}},"/profile":{"style.a89de.css":{"type":"style","weight":1},"bundle.38f5b.js":{"type":"script","weight":1},"route-profile.chunk.e67c6.js":{"type":"script","weight":0.9}},"/login":{"style.a89de.css":{"type":"style","weight":1},"bundle.38f5b.js":{"type":"script","weight":1},"route-login.chunk.22dcc.js":{"type":"script","weight":0.9}},"/confirm-account":{"style.a89de.css":{"type":"style","weight":1},"bundle.38f5b.js":{"type":"script","weight":1},"route-confirm-account.chunk.1d5aa.js":{"type":"script","weight":0.9}}}